Workbook

Sheet Lisez-moi
A1: Amundi — reconstitution des comptes 2010-2025 (étude n° 2, chapitre 15)
A2: Établi le 20/10/2026 à partir des sources primaires listées dans claude/etude-02-amundi-SOURCES.md.
A3: Conventions : M€ sauf mention ; valeurs saisies en bleu, formules en noir ; série comptable = dernier retraitement connu, chaque retraitement est consigné dans l'onglet Ruptures_retraitements.
A4: Les documents téléchargés depuis about.amundi.com sont les versions anglaises (traductions libres) ; les chiffres sont identiques à la version française déposée à l'AMF, qui fait foi pour les citations.
A5: 2010-2011 : comptes IFRS d'Amundi Group (rapport d'activité 2011). 2012-2014 : document de base de l'IPO. 2015-2025 : URD et communiqués annuels.
A6: Limites connues : 2012-2013 au million près seulement ; incorporels 2012-2013 non isolés ; indicateurs ajustés antérieurs à 2016 selon des définitions différentes.

Sheet CR_comptable
A1: Compte de résultat consolidé IFRS, tel que publié (dernier retraitement connu)
A2: M€ — bleu : saisi depuis la source ; noir : formule
A4: Ligne | B4: 2010 | C4: 2011 | D4: 2012 | E4: 2013 | F4: 2014 | G4: 2015 | H4: 2016 | I4: 2017 | J4: 2018 | K4: 2019 | L4: 2020 | M4: 2021 | N4: 2022 | O4: 2023 | P4: 2024 | Q4: 2025 | R4: Source / remarque
A5: Produit net / revenus nets (IFRS) | B5: 1483.7 | C5: 1394 | D5: 1456 | E5: 1438 | F5: 1537.5 | G5: 1656.9 | H5: 1677.4 | I5: 2257.1 | J5: 2510.4 | K5: 2636.2 | L5: 2521.2 | M5: 3136 | N5: 3055.5 | O5: 3122.2 | P5: 3405.9 | Q5: 3341.7 | R5: 2010-11 : rapport 2011 p.49 ; 2012-13 : document de base ch.3 ; 2014 : URD 2015 (retraité IFRIC 21) ; 2015-2025 : URD n, comptes consolidés 6.2.1
A6: Charges générales d'exploitation | B6: -874.1 | C6: -764.6 | D6: -756 | E6: -773 | F6: -805.1 | G6: -883.2 | H6: -877.8 | I6: -1308.6 | J6: -1387.2 | K6: -1376.8 | L6: -1340.8 | M6: -1550.2 | N6: -1732.7 | O6: -1706 | P6: -1851.6 | Q6: -1895.4 | R6: idem
A7: Résultat brut d'exploitation | B7: =B5+B6 -> 609.6 | C7: =C5+C6 -> 629.4 | D7: =D5+D6 -> 700 | E7: =E5+E6 -> 665 | F7: =F5+F6 -> 732.4 | G7: =G5+G6 -> 773.7 | H7: =H5+H6 -> 799.6 | I7: =I5+I6 -> 948.5 | ... Q7: =Q5+Q6 -> 1446.3 | R7: calculé = revenus + charges
A8: Coût du risque | B8: -1.8 | C8: 7 | D8: 3 | E8: -7 | F8: -4.8 | G8: -6.6 | H8: -0.6 | I8: -13.3 | J8: -11.2 | K8: -10.7 | L8: -22.8 | M8: -12.1 | N8: -12.1 | O8: -2.6 | P8: -9.8 | Q8: -8.7 | R8: idem
A9: Quote-part des sociétés mises en équivalence | B9: 3.5 | C9: 10.9 | D9: 10 | E9: 16 | F9: 16.9 | G9: 25.2 | H9: 28.5 | I9: 33.1 | J9: 49.7 | K9: 46.3 | L9: 66 | M9: 84.3 | N9: 88.2 | O9: 102 | P9: 123.3 | Q9: 201.3 | R9: 2025 : JV 135 + Victory Capital 66
A10: Gains/pertes sur autres actifs | B10: -1.6 | C10: 0.3 | D10: 0 | E10: 0 | F10: 0 | G10: 13.6 | H10: 0 | I10: -1.3 | J10: -0.1 | K10: 0 | L10: 0 | M10: -0.1 | N10: 4 | O10: -4.9 | P10: 0.1 | Q10: 402.4 | R10: 2025 : déconsolidation d'Amundi US (apport à Victory Capital)
A11: Résultat avant impôt | B11: =B7+B8+B9+B10 -> 609.7 | C11: =C7+C8+C9+C10 -> 647.6 | D11: =D7+D8+D9+D10 -> 713 | E11: =E7+E8+E9+E10 -> 674 | F11: =F7+F8+F9+F10 -> 744.5 | G11: =G7+G8+G9+G10 -> 805.9 | H11: =H7+H8+H9+H10 -> 827.5 | I11: =I7+I8+I9+I10 -> 967 | ... Q11: =Q7+Q8+Q9+Q10 -> 2041.3 | R11: calculé
A12: Impôt | B12: -205.2 | C12: -223.8 | D12: -226 | E12: -222 | F12: -254 | G12: -286 | H12: -258.4 | I12: -285.9 | J12: -306.8 | K12: -335.7 | L12: -316.6 | M12: -291.8 | N12: -328.7 | O12: -350.8 | P12: -365.5 | Q12: -452 | R12: 2021 inclut Affrancamento +114
A13: Résultat net de l'exercice | B13: =B11+B12 -> 404.5 | C13: =C11+C12 -> 423.8 | D13: =D11+D12 -> 487 | E13: =E11+E12 -> 452 | F13: =F11+F12 -> 490.5 | G13: =G11+G12 -> 519.9 | H13: =H11+H12 -> 569.1 | I13: =I11+I12 -> 681.1 | ... Q13: =Q11+Q12 -> 1589.3 | R13: calculé
A14: Résultat net part du groupe (publié) | B14: 403.9 | C14: 422.6 | D14: 486 | E14: 451 | F14: 489.7 | G14: 518.6 | H14: 568.3 | I14: 681.3 | J14: 855 | K14: 959.3 | L14: 909.8 | M14: 1369.5 | N14: 1073.7 | O14: 1164.9 | P14: 1305.1 | Q14: 1592.2 | R14: publié ; écart avec la ligne précédente = intérêts minoritaires
A15: Coefficient d'exploitation comptable % | B15: =-B6/B5 -> 0.58913527 | C15: =-C6/C5 -> 0.54849354 | D15: =-D6/D5 -> 0.51923077 | E15: =-E6/E5 -> 0.53755216 | F15: =-F6/F5 -> 0.52364228 | G15: =-G6/G5 -> 0.53304364 | H15: =-H6/H5 -> 0.52330988 | I15: =-I6/I5 -> 0.5797705 | ... Q15: =-Q6/Q5 -> 0.56719634 | R15: calculé = charges / revenus

Sheet CR_ajuste
A1: Indicateurs de gestion et résultat ajusté (définitions Amundi)
A2: M€
A4: Ligne | B4: 2010 | C4: 2011 | D4: 2012 | E4: 2013 | F4: 2014 | G4: 2015 | H4: 2016 | I4: 2017 | J4: 2018 | K4: 2019 | L4: 2020 | M4: 2021 | N4: 2022 | O4: 2023 | P4: 2024 | Q4: 2025 | R4: Source / remarque
A5: Commissions nettes de gestion | B5: 1359 | C5: 1315 | D5: 1211 | E5: 1238 | F5: 1322 | G5: 1466 | H5: 1510 | I5: 2029 | J5: 2491 | K5: 2493 | L5: 2434 | M5: 2757 | N5: 2965 | O5: 2940 | P5: 3184 | Q5: 3052 | R5: 2010-11 présentation de gestion (2010 pro forma BFT) ; 2021 retraité (2 786 publié) ; 2024 publié (pro forma hors Amundi US : 2 930)
A6: Commissions de surperformance | B6: 138 | C6: 72 | D6: 166 | E6: 162 | F6: 170 | G6: 138 | H6: 115 | I6: 175 | J6: 115 | K6: 171 | L6: 200 | M6: 427 | N6: 171 | O6: 123 | P6: 145 | Q6: 173 | R6: 2021 : 261 M€ jugés exceptionnels par Amundi (revenus normalisés)
A7: Amundi Technology | M7: 36 | N7: 48 | O7: 60 | P7: 80 | Q7: 116 | R7: ligne isolée depuis 2021
A8: Revenus nets ajustés | H8: 1694 | I8: 2301 | J8: 2582 | K8: 2707 | L8: 2595 | M8: 3204 | N8: 3137 | O8: 3204 | P8: 3497 | Q8: 3417 | R8: définition Amundi : hors amortissement des contrats de distribution / incorporels ; 2024 pro forma hors US : 3 231
A9: Charges ajustées | H9: -878 | I9: -1173 | J9: -1331 | K9: -1377 | L9: -1341 | M9: -1534 | N9: -1671 | O9: -1706 | P9: -1837 | Q9: -1781 | R9: hors coûts d'intégration (Pioneer, Lyxor, aixigo) ; 2024 PF : -1 677
A10: Résultat net part du groupe ajusté | B10: 413 | C10: 423 | D10: 427 | E10: 451 | F10: 490 | G10: 528 | H10: 579 | I10: 800 | J10: 946 | K10: 1009 | L10: 962 | M10: 1315 | N10: 1178 | O10: 1224 | P10: 1382 | Q10: 1354 | R10: 2010-11 gestion ; 2012 hors plus-value HLA ; 2015 hors frais d'IPO ; 2017 combiné Amundi+Pioneer : 918 ; 2021 normalisé : 1 158
A11: Coefficient d'exploitation ajusté % | B11: =IFERROR(-B9/B8,"") | C11: =IFERROR(-C9/C8,"") | D11: =IFERROR(-D9/D8,"") | E11: =IFERROR(-E9/E8,"") | F11: =IFERROR(-F9/F8,"") | G11: =IFERROR(-G9/G8,"") | H11: =IFERROR(-H9/H8,"") -> 0.51829988 | I11: =IFERROR(-I9/I8,"") -> 0.50977836 | ... Q11: =IFERROR(-Q9/Q8,"") -> 0.52121744 | R11: calculé

Sheet Encours_collecte
A1: Encours sous gestion et collecte nette
A2: Md€
A4: Ligne | B4: 2010 | C4: 2011 | D4: 2012 | E4: 2013 | F4: 2014 | G4: 2015 | H4: 2016 | I4: 2017 | J4: 2018 | K4: 2019 | L4: 2020 | M4: 2021 | N4: 2022 | O4: 2023 | P4: 2024 | Q4: 2025 | R4: Source / remarque
A5: Encours fin d'année, y.c. JV (Md€) | B5: 710.3 | C5: 658.6 | D5: 748.5 | E5: 792 | F5: 877.6 | G5: 985 | H5: 1083 | I5: 1426 | J5: 1425 | K5: 1653 | L5: 1729 | M5: 2064 | N5: 1904 | O5: 2037 | P5: 2240 | Q5: 2380 | R5: 2010 pro forma BFT ; 2012 : changement de méthode (JV à 100 %) ; 2017 Pioneer ; 2021 Lyxor (148) ; 2025 hors Amundi US, VCTR non compté
A6: dont JV (Md€) | D6: 21.6 | E6: 25.8 | F6: 38 | G6: 73 | H6: 99 | I6: 118 | J6: 142 | K6: 234 | L6: 239 | M6: 286 | N6: 296 | O6: 316 | P6: 372 | Q6: 364 | R6: SBI FM, ABC-CA, NH-Amundi, Wafa (34 %)
A7: Encours hors JV (Md€) | B7: =IF(B6="","",B5-B6) | C7: =IF(C6="","",C5-C6) | D7: =IF(D6="","",D5-D6) -> 726.9 | E7: =IF(E6="","",E5-E6) -> 766.2 | F7: =IF(F6="","",F5-F6) -> 839.6 | G7: =IF(G6="","",G5-G6) -> 912 | H7: =IF(H6="","",H5-H6) -> 984 | I7: =IF(I6="","",I5-I6) -> 1308 | ... Q7: =IF(Q6="","",Q5-Q6) -> 2016 | R7: calculé
A8: Collecte nette, y.c. JV (Md€) | B8: 1.2 | C8: -35 | D8: 17.6 | E8: 11.1 | F8: 32.5 | G8: 79.9 | H8: 62.2 | I8: 70.6 | J8: 42 | K8: 107.7 | L8: 45.1 | M8: 60.2 | N8: 7 | O8: 25.8 | P8: 55.4 | Q8: 87.6 | R8: communiqués annuels (colonne exercice ; 2017 combiné avec Pioneer) — 2021 et 2022 corrigés le 20/10/2026 (60,2 et 7,0 ; 65,6 et 15,0 étaient les chiffres du T4)
A9: Collecte / encours début % | C9: =C8/B5 -> -0.049274954 | D9: =D8/C5 -> 0.026723353 | E9: =E8/D5 -> 0.014829659 | F9: =F8/E5 -> 0.041035354 | G9: =G8/F5 -> 0.091043756 | H9: =H8/G5 -> 0.063147208 | I9: =I8/H5 -> 0.065189289 | J9: =J8/I5 -> 0.029453015 | ... Q9: =Q8/P5 -> 0.039107143 | R9: calculé

Sheet Bilan
A1: Postes clés du bilan consolidé
A2: M€ au 31/12
A4: Ligne | B4: 2010 | C4: 2011 | D4: 2012 | E4: 2013 | F4: 2014 | G4: 2015 | H4: 2016 | I4: 2017 | J4: 2018 | K4: 2019 | L4: 2020 | M4: 2021 | N4: 2022 | O4: 2023 | P4: 2024 | Q4: 2025 | R4: Source / remarque
A5: Capitaux propres part du groupe | B5: 5248.7 | C5: 5418 | D5: 5687 | E5: 5816 | F5: 6123.3 | G5: 6406.8 | H5: 6644.4 | I5: 8203 | J5: 8528.1 | K5: 8900 | L5: 9695.2 | M5: 10670.8 | N5: 11025.8 | O5: 11369.1 | P5: 12002.6 | Q5: 12655.3 | R5: 2017 retraité IFRS 9 à 8 200 dans l'URD 2018
A6: Écarts d'acquisition | B6: 2885.8 | C6: 2886.5 | D6: 2876 | E6: 2894 | F6: 2913.9 | G6: 2998.5 | H6: 3161.5 | I6: 5674 | J6: 5695.5 | K6: 5711.7 | L6: 5995.6 | M6: 6703.6 | N6: 6731.2 | O6: 6707.7 | P6: 6572.2 | Q6: 6560.6
A7: Immobilisations incorporelles | B7: 207 | C7: 187.6 | F7: 96.5 | G7: 111.2 | H7: 107.9 | I7: 623.2 | J7: 544.2 | K7: 485.1 | L7: 530.5 | M7: 518.8 | N7: 451.4 | O7: 385.1 | P7: 414.3 | Q7: 365.4 | R7: 2012-13 : non isolées dans le document de base
A8: Fonds propres tangibles (calcul brut) | B8: =IF(B7="","",B5-B6-B7) -> 2155.9 | C8: =IF(C7="","",C5-C6-C7) -> 2343.9 | D8: =IF(D7="","",D5-D6-D7) | E8: =IF(E7="","",E5-E6-E7) | F8: =IF(F7="","",F5-F6-F7) -> 3112.9 | G8: =IF(G7="","",G5-G6-G7) -> 3297.1 | H8: =IF(H7="","",H5-H6-H7) -> 3375 | I8: =IF(I7="","",I5-I6-I7) -> 1905.8 | ... Q8: =IF(Q7="","",Q5-Q6-Q7) -> 5729.3 | R8: calculé = CP − écarts d'acquisition − incorporels ; Amundi publie une mesure propre (4,9 Md€ fin 2025)
A9: Total bilan | B9: 8298.8 | C9: 8996 | D9: 11599 | E9: 12620 | F9: 13248 | G9: 12931.8 | H9: 13918 | I9: 18819 | J9: 20937.2 | K9: 24261.4 | L9: 28888.2 | M9: 28718 | N9: 28616.7 | O9: 36010.8 | P9: 38302.4 | Q9: 38743.7 | R9: 2025 reconstitué : passif 26 042,3 + CP 12 701,4

Sheet Action
A1: Données par action
A4: Ligne | B4: 2010 | C4: 2011 | D4: 2012 | E4: 2013 | F4: 2014 | G4: 2015 | H4: 2016 | I4: 2017 | J4: 2018 | K4: 2019 | L4: 2020 | M4: 2021 | N4: 2022 | O4: 2023 | P4: 2024 | Q4: 2025 | R4: Source / remarque
A5: Actions en fin d'année (millions) | D5: 166.79 | E5: 166.79 | F5: 166.79 | G5: 167.245 | H5: 167.925 | I5: 201.511 | J5: 201.704 | K5: 202.163 | L5: 202.586 | M5: 203.075 | N5: 203.86 | O5: 204.648 | P5: 205.419 | Q5: 206.386 | R5: communiqués / supplément ; 2017 : augmentation de capital Pioneer
A6: Dividende par action (€), au titre de l'exercice | C6: 1.39 | D6: 1.6 | E6: 1.35 | F6: 1.46 | G6: 2.05 | H6: 2.2 | I6: 2.5 | J6: 2.9 | K6: 0 | L6: 2.9 | M6: 4.1 | N6: 4.1 | O6: 4.1 | P6: 4.25 | Q6: 4.25 | R6: 2019 : aucun dividende (recommandation BCE, conseil du 01/04/2020) ; 2025 proposé à l'AG du 02/06/2026
A7: Dividende total (M€) | G7: 343 | H7: 443 | I7: 504 | J7: 583 | K7: 0 | L7: 587 | M7: 832 | N7: 836 | O7: 839 | P7: 873 | Q7: 877 | R7: URD 2025, politique de distribution
A8: Taux de distribution publié % | G8: 0.65 | H8: 0.65 | I8: 0.655 | J8: 0.653 | K8: 0 | L8: 0.646 | M8: 0.656 | N8: 0.747 | O8: 0.72 | P8: 0.67 | Q8: 0.737 | R8: idem

Sheet Pont_encours
A1: Décomposition de la variation des encours
A2: Md€
A4: Ligne | B4: 2010 | C4: 2011 | D4: 2012 | E4: 2013 | F4: 2014 | G4: 2015 | H4: 2016 | I4: 2017 | J4: 2018 | K4: 2019 | L4: 2020 | M4: 2021 | N4: 2022 | O4: 2023 | P4: 2024 | Q4: 2025 | R4: Source / remarque
A5: Collecte nette | F5: 32.5 | G5: 79.9 | H5: 62.2 | I5: 70.6 | J5: 42 | K5: 107.7 | L5: 45.1 | M5: 60.2 | N5: 7 | O5: 25.8 | P5: 55.4 | Q5: 87.6 | R5: communiqués annuels
A6: Effet marché et change | G6: 22.4 | H6: 21.8 | I6: 27.4 | J6: -43.1 | K6: 120.6 | L6: 9.5 | N6: -167 | O6: 127.2 | P6: 139.8 | Q6: 61.9 | R6: somme des trimestres publiés ; 2025 = marché +154,9 et change −93,0 ; 2021 en résidu
A7: Effet périmètre | G7: 5.3 | H7: 13.6 | I7: 242.9 | J7: 0 | K7: 0 | L7: 20.7 | M7: 148 | N7: 0 | O7: -20 | P7: 7.9 | Q7: -9.7 | R7: 2015 BAWAG ; 2016 KBI, CAI ; 2017 Pioneer ; 2020 Sabadell ; 2021 Lyxor ; 2023 cession Lyxor Inc. ; 2024 Alpha ; 2025 Amundi US/Victory
A8: Encours fin (Md€) | B8: 710.3 | C8: 658.6 | D8: 748.5 | E8: 792 | F8: 877.6 | G8: 985 | H8: 1083 | I8: 1426 | J8: 1425 | K8: 1653 | L8: 1729 | M8: 2064 | N8: 1904 | O8: 2037 | P8: 2240 | Q8: 2380
A9: Résidu de contrôle | C9: =IF(OR(C5="",C6=""),"",C8-B8-C5-C6-C7) | D9: =IF(OR(D5="",D6=""),"",D8-C8-D5-D6-D7) | E9: =IF(OR(E5="",E6=""),"",E8-D8-E5-E6-E7) | F9: =IF(OR(F5="",F6=""),"",F8-E8-F5-F6-F7) | G9: =IF(OR(G5="",G6=""),"",G8-F8-G5-G6-G7) -> -0.2 | H9: =IF(OR(H5="",H6=""),"",H8-G8-H5-H6-H7) -> 0.4 | I9: =IF(OR(I5="",I6=""),"",I8-H8-I5-I6-I7) -> 2.1 | J9: =IF(OR(J5="",J6=""),"",J8-I8-J5-J6-J7) -> 0.1 | ... Q9: =IF(OR(Q5="",Q6=""),"",Q8-P8-Q5-Q6-Q7) -> 0.2 | R9: =encours fin − encours début − collecte − marché − périmètre (doit être ~0 ; 2021 : marché déduit) -> #N/A
A10: Croissance organique % (collecte / encours début) | C10: =IF(C5="","",C5/B8) | D10: =IF(D5="","",D5/C8) | E10: =IF(E5="","",E5/D8) | F10: =IF(F5="","",F5/E8) -> 0.041035354 | G10: =IF(G5="","",G5/F8) -> 0.091043756 | H10: =IF(H5="","",H5/G8) -> 0.063147208 | I10: =IF(I5="","",I5/H8) -> 0.065189289 | J10: =IF(J5="","",J5/I8) -> 0.029453015 | ... Q10: =IF(Q5="","",Q5/P8) -> 0.039107143
A11: Croissance par les marchés % (marché / encours début) | C11: =IF(C6="","",C6/B8) | D11: =IF(D6="","",D6/C8) | E11: =IF(E6="","",E6/D8) | F11: =IF(F6="","",F6/E8) | G11: =IF(G6="","",G6/F8) -> 0.025524157 | H11: =IF(H6="","",H6/G8) -> 0.02213198 | I11: =IF(I6="","",I6/H8) -> 0.025300092 | J11: =IF(J6="","",J6/I8) -> -0.030224404 | ... Q11: =IF(Q6="","",Q6/P8) -> 0.027633929

Sheet Charges_marges
A1: Charges, marges et productivité
A2: M€ sauf mention
A4: Ligne | B4: 2010 | C4: 2011 | D4: 2012 | E4: 2013 | F4: 2014 | G4: 2015 | H4: 2016 | I4: 2017 | J4: 2018 | K4: 2019 | L4: 2020 | M4: 2021 | N4: 2022 | O4: 2023 | P4: 2024 | Q4: 2025 | R4: Source / remarque
A5: Frais de personnel (IFRS) | F5: -509.3 | G5: -565.1 | H5: -557.4 | I5: -845.7 | J5: -857 | K5: -886.7 | L5: -896.8 | M5: -1045.8 | N5: -1120.6 | O5: -1144.6 | P5: -1263.1 | Q5: -1202.6 | R5: URD note 4.4 ; 2023 et 2025 en ajusté (supplément financier)
A6: Charges totales (IFRS) | F6: -805.1 | G6: -883.2 | H6: -877.8 | I6: -1308.6 | J6: -1387.2 | K6: -1376.8 | L6: -1340.8 | M6: -1550.2 | N6: -1732.7 | O6: -1706 | P6: -1851.6 | Q6: -1895.4
A7: Autres charges | B7: =IF(B5="","",B6-B5) | C7: =IF(C5="","",C6-C5) | D7: =IF(D5="","",D6-D5) | E7: =IF(E5="","",E6-E5) | F7: =IF(F5="","",F6-F5) -> -295.8 | G7: =IF(G5="","",G6-G5) -> -318.1 | H7: =IF(H5="","",H6-H5) -> -320.4 | I7: =IF(I5="","",I6-I5) -> -462.9 | ... Q7: =IF(Q5="","",Q6-Q5) -> -692.8 | R7: calculé
A8: Part du personnel % | B8: =IF(B5="","",B5/B6) | C8: =IF(C5="","",C5/C6) | D8: =IF(D5="","",D5/D6) | E8: =IF(E5="","",E5/E6) | F8: =IF(F5="","",F5/F6) -> 0.63259222 | G8: =IF(G5="","",G5/G6) -> 0.63983243 | H8: =IF(H5="","",H5/H6) -> 0.63499658 | I8: =IF(I5="","",I5/I6) -> 0.64626318 | ... Q8: =IF(Q5="","",Q5/Q6) -> 0.63448349 | R8: calculé
A9: Marge sur commissions publiée (pb) | B9: 19.2 | C9: 18.8 | F9: 16.4 | G9: 16.1 | H9: 16 | I9: 19.1 | J9: 18.8 | K9: 18.4 | L9: 17.4 | M9: 17.5 | N9: 17.8 | O9: 17.7 | P9: 17.7 | Q9: 16.1 | R9: 2010-11 R2011 ; 2014-17 URD ; 2017 combiné ; 2025 : 15,9 à périmètre comparable
A10: Encours moyens hors JV implicites (Md€) | B10: =IFERROR(CR_ajuste!B5/B9*10,"") -> 707.8125 | C10: =IFERROR(CR_ajuste!C5/C9*10,"") -> 699.46809 | D10: =IFERROR(CR_ajuste!D5/D9*10,"") | E10: =IFERROR(CR_ajuste!E5/E9*10,"") | F10: =IFERROR(CR_ajuste!F5/F9*10,"") -> 806.09756 | G10: =IFERROR(CR_ajuste!G5/G9*10,"") -> 910.55901 | H10: =IFERROR(CR_ajuste!H5/H9*10,"") -> 943.75 | I10: =IFERROR(CR_ajuste!I5/I9*10,"") -> 1062.3037 | ... Q10: =IFERROR(CR_ajuste!Q5/Q9*10,"") -> 1895.6522 | R10: =commissions de gestion / marge -> #VALUE!
A11: Effectif fin d'année (ETP, ordre de grandeur) | B11: 2915 | C11: 2902 | L11: 4500 | M11: 5300 | N11: 5400 | O11: 5500 | P11: 5700 | Q11: 5366 | R11: R2011 ; communiqués ; 2025 URD (ETP consolidés)

Sheet Ruptures_retraitements
A1: Année | B1: Nature | C1: Effet | D1: Traitement dans la série | E1: Source
A2: 2010 | B2: Création d'Amundi (CAAM + SGAM), charges de fusion | C2: Éléments extraordinaires −81 M€ (présentation de gestion) | D2: Comptable et gestion présentés séparément | E2: Rapport 2011 p.11
A3: 2011 | B3: Acquisition de BFT Gestion (01/07/2011, consolidée au 01/01) | C3: 2010 pro forma en présentation de gestion | D3: 2010 gestion pro forma ; 2010 IFRS non retraité | E3: Rapport 2011
A4: 2011 | B4: Rupture de présentation PNB → revenus nets | C4: Définitions différentes 2011/2012 | D4: À réconcilier avant lecture longue | E4: Rapport 2011 / document de base
A5: 2012 | B5: Plus-value de cession de HLA | C5: +59,9 M€ avant impôt | D5: RN ajusté 2012 hors HLA = 427 | E5: Document de base ch.3
A6: 2014 | B6: Application rétrospective d'IFRIC 21 | C6: Revenus 1 540 → 1 538 ; charges 810 → 805 | D6: Valeur retraitée retenue | E6: URD 2015
A7: 2015 | B7: Frais d'introduction en Bourse | C7: 15 M€ avant impôt, 9 M€ après | D7: RN ajusté 528 vs publié 519 | E7: CP T4 2015
A8: 2016 | B8: Amortissement des contrats de distribution (SG, Bawag) | C8: ~17 M€ avant impôt | D8: Exclu du résultat ajusté à partir de 2017 | E8: CP T4 2017
A9: 2017 | B9: Pioneer Investments consolidé au 01/07/2017 | C9: Revenus +~420 M€ au S2 ; coûts d'intégration 135 M€ avant impôt | D9: Comptes combinés publiés en parallèle | E9: CP T4 2017
A10: 2018 | B10: Fin des coûts d'intégration Pioneer (56 M€) ; IFRS 9 | C10: CP 2017 retraités à 8 200 | D10: — | E10: CP T4 2018, URD 2018
A11: 2019 | B11: Dividende 2019 supprimé (BCE) | C11: — | D11: Dividende 0 | E11: URD 2025
A12: 2021 | B12: Affrancamento (Italie) | C12: +114 M€ d'impôt différé, sans flux | D12: Exclu du résultat ajusté | E12: CP T4 2021
A13: 2021 | B13: Commissions de surperformance exceptionnelles | C13: 261 M€ de revenus, 44 M€ de coûts associés | D13: Résultat « normalisé » 1 158 | E13: CP T4 2022
... A20: 2026 | B20: Introduction en Bourse de SBI FM (cession 3,7 %) | C20: Plus-value nette ≈ 300 M€ au T3 2026 | D20: À exclure de la normalisation | E20: CP 17/07/2026

Sheet Macro
A1: Macroéconomie et marchés 2010-2026 (BCE, FRED ; 2026 au 16/10)
A3: Année | B3: Taux dépôt BCE fin % | C3: IPCH déc. % | D3: PIB zone euro % | E3: OAT 10a % | F3: Bund 10a % | G3: BTP 10a % | H3: EUR/USD | I3: Euro Stoxx 50 | J3: ES50 var % | K3: Euro Stoxx var % | L3: Nasdaq var %
A4: 2010 | B4: 0.25 | C4: 2.2 | D4: 2 | E4: 3.34 | F4: 2.91 | G4: 4.603 | H4: 1.3362 | I4: 2826 | J4: -2.8 | K4: 2.4 | L4: 16.9
A5: 2011 | B5: 0.25 | C5: 2.8 | D5: 1.8 | E5: 3.16 | F5: 1.93 | G5: 6.812 | H5: 1.2939 | I5: 2283 | J5: -19.2 | K5: -19.7 | L5: -1.8
A6: 2012 | B6: 0 | C6: 2.2 | D6: -0.9 | E6: 2.01 | F6: 1.3 | G6: 4.542 | H6: 1.3194 | I6: 2626 | J6: 15 | K6: 16.9 | L6: 15.9
A7: 2013 | B7: 0 | C7: 0.8 | D7: -0.1 | E7: 2.33 | F7: 1.8 | G7: 4.114 | H7: 1.3791 | I7: 3010 | J7: 14.7 | K7: 17.4 | L7: 38.3
A8: 2014 | B8: -0.2 | C8: -0.2 | D8: 1.5 | E8: 0.92 | F8: 0.59 | G8: 1.99 | H8: 1.2141 | I8: 3160 | J8: 5 | K8: 5 | L8: 13.4
A9: 2015 | B9: -0.3 | C9: 0.3 | D9: 2 | E9: 0.93 | F9: 0.55 | G9: 1.579 | H9: 1.0887 | I9: 3289 | J9: 4.1 | K9: 8.1 | L9: 5.7
A10: 2016 | B10: -0.4 | C10: 1.1 | D10: 1.8 | E10: 0.75 | F10: 0.25 | G10: 1.886 | H10: 1.0541 | I10: 3207 | J10: -2.5 | K10: -1 | L10: 7.5
A11: 2017 | B11: -0.4 | C11: 1.3 | D11: 2.8 | E11: 0.67 | F11: 0.3 | G11: 1.795 | H11: 1.1993 | I11: 3565 | J11: 11.1 | K11: 13.8 | L11: 28.2
A12: 2018 | B12: -0.4 | C12: 1.5 | D12: 1.8 | E12: 0.7 | F12: 0.19 | G12: 2.975 | H12: 1.145 | I12: 3058 | J12: -14.2 | K12: -14 | L12: -3.9
A13: 2019 | B13: -0.5 | C13: 1.3 | D13: 1.6 | E13: 0.04 | F13: -0.3 | G13: 1.37 | H13: 1.1234 | I13: 3715 | J13: 21.5 | K13: 19.6 | L13: 35.2
A14: 2020 | B14: -0.5 | C14: -0.3 | D14: -6.2 | E14: -0.34 | F14: -0.618 | G14: 0.578 | H14: 1.2271 | I14: 3531 | J14: -5 | K14: -1.7 | L14: 43.6
A15: 2021 | B15: -0.5 | C15: 5 | D15: 6.6 | E15: 0.05 | F15: -0.383 | G15: 1.047 | H15: 1.1326 | I15: 4208 | J15: 19.2 | K15: 19 | L15: 21.4
... A19: 2025 | B19: 2 | C19: 1.9 | D19: 1.3 | E19: 3.56 | F19: 2.813 | G19: 3.552 | H19: 1.175 | I19: 5731 | J19: 16.5 | K19: 19.1 | L19: 20.4
A20: 2026 | B20: 2.5 | D20: 0.5 | E20: 4.44 | F20: 3.473 | G20: 4.362 | H20: 1.1225 | I20: 6316 | J20: 10.2 | K20: 10.2 | L20: 13.7
